{"trial_id": "09", "hyperparameters": {"space": [{"class_name": "Int", "config": {"name": "num_layers", "default": null, "conditions": [], "min_value": 1, "max_value": 10, "step": 1, "sampling": "linear"}}, {"class_name": "Choice", "config": {"name": "num_units_0", "default": 8, "conditions": [], "values": [8, 16, 32, 64, 128], "ordered": true}}, {"class_name": "Choice", "config": {"name": "activation_0", "default": "relu", "conditions": [], "values": ["relu", "tanh", "sigmoid", "linear"], "ordered": false}}, {"class_name": "Choice", "config": {"name": "optimizer", "default": "adadelta", "conditions": [], "values": ["adadelta", "adagrad", "adam", "adamax", "ftrl", "nadam", "rmsprop"], "ordered": false}}, {"class_name": "Choice", "config": {"name": "num_units_1", "default": 8, "conditions": [], "values": [8, 16, 32, 64, 128], "ordered": true}}, {"class_name": "Choice", "config": {"name": "activation_1", "default": "relu", "conditions": [], "values": ["relu", "tanh", "sigmoid", "linear"], "ordered": false}}, {"class_name": "Choice", "config": {"name": "num_units_2", "default": 8, "conditions": [], "values": [8, 16, 32, 64, 128], "ordered": true}}, {"class_name": "Choice", "config": {"name": "activation_2", "default": "relu", "conditions": [], "values": ["relu", "tanh", "sigmoid", "linear"], "ordered": false}}, {"class_name": "Choice", "config": {"name": "num_units_3", "default": 8, "conditions": [], "values": [8, 16, 32, 64, 128], "ordered": true}}, {"class_name": "Choice", "config": {"name": "activation_3", "default": "relu", "conditions": [], "values": ["relu", "tanh", "sigmoid", "linear"], "ordered": false}}, {"class_name": "Choice", "config": {"name": "num_units_4", "default": 8, "conditions": [], "values": [8, 16, 32, 64, 128], "ordered": true}}, {"class_name": "Choice", "config": {"name": "activation_4", "default": "relu", "conditions": [], "values": ["relu", "tanh", "sigmoid", "linear"], "ordered": false}}, {"class_name": "Choice", "config": {"name": "num_units_5", "default": 8, "conditions": [], "values": [8, 16, 32, 64, 128], "ordered": true}}, {"class_name": "Choice", "config": {"name": "activation_5", "default": "relu", "conditions": [], "values": ["relu", "tanh", "sigmoid", "linear"], "ordered": false}}, {"class_name": "Choice", "config": {"name": "num_units_6", "default": 8, "conditions": [], "values": [8, 16, 32, 64, 128], "ordered": true}}, {"class_name": "Choice", "config": {"name": "activation_6", "default": "relu", "conditions": [], "values": ["relu", "tanh", "sigmoid", "linear"], "ordered": false}}, {"class_name": "Choice", "config": {"name": "num_units_7", "default": 8, "conditions": [], "values": [8, 16, 32, 64, 128], "ordered": true}}, {"class_name": "Choice", "config": {"name": "activation_7", "default": "relu", "conditions": [], "values": ["relu", "tanh", "sigmoid", "linear"], "ordered": false}}, {"class_name": "Choice", "config": {"name": "num_units_8", "default": 8, "conditions": [], "values": [8, 16, 32, 64, 128], "ordered": true}}, {"class_name": "Choice", "config": {"name": "activation_8", "default": "relu", "conditions": [], "values": ["relu", "tanh", "sigmoid", "linear"], "ordered": false}}, {"class_name": "Choice", "config": {"name": "num_units_9", "default": 8, "conditions": [], "values": [8, 16, 32, 64, 128], "ordered": true}}, {"class_name": "Choice", "config": {"name": "activation_9", "default": "relu", "conditions": [], "values": ["relu", "tanh", "sigmoid", "linear"], "ordered": false}}], "values": {"num_layers": 1, "num_units_0": 64, "activation_0": "sigmoid", "optimizer": "adagrad", "num_units_1": 16, "activation_1": "tanh", "num_units_2": 8, "activation_2": "linear", "num_units_3": 32, "activation_3": "sigmoid", "num_units_4": 128, "activation_4": "sigmoid", "num_units_5": 64, "activation_5": "sigmoid", "num_units_6": 64, "activation_6": "relu", "num_units_7": 32, "activation_7": "sigmoid", "num_units_8": 128, "activation_8": "relu", "num_units_9": 8, "activation_9": "relu"}}, "metrics": {"metrics": {"accuracy": {"direction": "max", "observations": [{"value": [0.34690552949905396], "step": 0}]}, "loss": {"direction": "min", "observations": [{"value": [0.7906965613365173], "step": 0}]}, "val_accuracy": {"direction": "max", "observations": [{"value": [0.3311688303947449], "step": 0}]}, "val_loss": {"direction": "min", "observations": [{"value": [0.7872142195701599], "step": 0}]}}}, "score": 0.3311688303947449, "best_step": 0, "status": "COMPLETED", "message": null}